LICENSE
reliesl/__init__.py
reliesl/cli/__init__.py
reliesl/cli/bump.py
reliesl/cli/release.py
reliesl-0.1.1.dist-info/entry_points.txt
reliesl-0.1.1.dist-info/LICENSE
reliesl-0.1.1.dist-info/WHEEL
reliesl-0.1.1.dist-info/METADATA
reliesl-0.1.1.dist-info/RECORD
